scpscraper/__init__.py
scpscraper/gdrive.py
scpscraper/scpscraper.py
scpscraper/test_scpscraper.py
scpscraper-1.0.1.dist-info/LICENSE
scpscraper-1.0.1.dist-info/METADATA
scpscraper-1.0.1.dist-info/WHEEL
scpscraper-1.0.1.dist-info/top_level.txt
scpscraper-1.0.1.dist-info/RECORD
