Metadata-Version: 2.1
Name: scpscraper
Version: 1.0.1
Summary: A Python library designed for scraping data from the SCP wiki.
Home-page: https://github.com/JaonHax/scp-scraper
Author: JaonHax
Author-email: jaonhax@gmail.com
License: MIT
Keywords: scp,foundation,webscraper,tensorflow,dataset
Platform: UNKNOWN
Classifier: Programming Language :: Python :: 3
Classifier: Programming Language :: Python :: 3 :: Only
Classifier: Programming Language :: Python :: 3.6
Classifier: Programming Language :: Python :: 3.7
Classifier: Programming Language :: Python :: 3.8
Classifier: License :: OSI Approved :: MIT License
Classifier: Operating System :: OS Independent
Classifier: Development Status :: 3 - Alpha
Classifier: Intended Audience :: Developers
Classifier: Natural Language :: English
Classifier: Topic :: Scientific/Engineering :: Artificial Intelligence
Requires-Python: >=3.6
Requires-Dist: beautifulsoup4 (>=4.9.1)
Requires-Dist: bs4 (>=0.0.1)
Requires-Dist: soupsieve (>=2.0.1)
Requires-Dist: tqdm (>=4.48.0)
Requires-Dist: lxml
